__init__.py
cherry_jwt/__init__.py
cherry_jwt/crypto.py
cherry_jwt/exceptions.py
cherry_jwt/jwt.py
cherry_jwt/util.py
cherry_jwt/verifier.py
cherry_jwt-0.0.2.dist-info/LICENSE
cherry_jwt-0.0.2.dist-info/METADATA
cherry_jwt-0.0.2.dist-info/WHEEL
cherry_jwt-0.0.2.dist-info/top_level.txt
cherry_jwt-0.0.2.dist-info/RECORD
