Metadata-Version: 2.1
Name: cherry-jwt
Version: 0.0.2
Summary: Python JWT implementation
Author: Addison Cox
License: Copyright 2022 Addison Cox
Classifier: License :: OSI Approved :: MIT License
Classifier: Programming Language :: Python
Classifier: Programming Language :: Python :: 3
Requires-Python: >=3.7
License-File: LICENSE
Requires-Dist: cffi (>=1.15.1)
Requires-Dist: cryptography (>=38.0.4)
Requires-Dist: pycparser (>=2.21)
Requires-Dist: setuptools (>=63.2.0)
Requires-Dist: starkbank-ecdsa (>=2.2.0)
